finsy/__init__.py
finsy/controller.py
finsy/futures.py
finsy/gnmiclient.py
finsy/gnmipath.py
finsy/gnmistring.py
finsy/grpcutil.py
finsy/log.py
finsy/macaddr.py
finsy/p4arbitrator.py
finsy/p4client.py
finsy/p4entity.py
finsy/p4schema.py
finsy/p4values.py
finsy/pbutil.py
finsy/ports.py
finsy/proto/__init__.py
finsy/proto/gnmi1/__init__.py
finsy/proto/gnmi1/gnmi.proto
finsy/proto/gnmi1/gnmi_ext.proto
finsy/proto/gnmi1/gnmi_ext_pb2.py
finsy/proto/gnmi1/gnmi_ext_pb2.pyi
finsy/proto/gnmi1/gnmi_pb2.py
finsy/proto/gnmi1/gnmi_pb2.pyi
finsy/proto/gnmi1/gnmi_pb2_grpc.py
finsy/proto/gnmi1/gnmi_pb2_grpc.pyi
finsy/proto/google/rpc/__init__.py
finsy/proto/google/rpc/code.proto
finsy/proto/google/rpc/code_pb2.py
finsy/proto/google/rpc/code_pb2.pyi
finsy/proto/google/rpc/context/__init__.py
finsy/proto/google/rpc/context/attribute_context.proto
finsy/proto/google/rpc/context/attribute_context_pb2.py
finsy/proto/google/rpc/context/attribute_context_pb2.pyi
finsy/proto/google/rpc/error_details.proto
finsy/proto/google/rpc/error_details_pb2.py
finsy/proto/google/rpc/error_details_pb2.pyi
finsy/proto/google/rpc/status.proto
finsy/proto/google/rpc/status_pb2.py
finsy/proto/google/rpc/status_pb2.pyi
finsy/proto/p4/__init__.py
finsy/proto/p4/config/__init__.py
finsy/proto/p4/config/v1/__init__.py
finsy/proto/p4/config/v1/p4info.proto
finsy/proto/p4/config/v1/p4info_pb2.py
finsy/proto/p4/config/v1/p4info_pb2.pyi
finsy/proto/p4/config/v1/p4types.proto
finsy/proto/p4/config/v1/p4types_pb2.py
finsy/proto/p4/config/v1/p4types_pb2.pyi
finsy/proto/p4/v1/__init__.py
finsy/proto/p4/v1/p4data.proto
finsy/proto/p4/v1/p4data_pb2.py
finsy/proto/p4/v1/p4data_pb2.pyi
finsy/proto/p4/v1/p4runtime.proto
finsy/proto/p4/v1/p4runtime_pb2.py
finsy/proto/p4/v1/p4runtime_pb2.pyi
finsy/proto/p4/v1/p4runtime_pb2_grpc.py
finsy/proto/p4/v1/p4runtime_pb2_grpc.pyi
finsy/proto/p4testgen1/__init__.py
finsy/proto/p4testgen1/p4testgen.proto
finsy/proto/p4testgen1/p4testgen_pb2.py
finsy/proto/p4testgen1/p4testgen_pb2.pyi
finsy-0.28.0.dist-info/LICENSE.txt
finsy-0.28.0.dist-info/METADATA
finsy-0.28.0.dist-info/WHEEL
finsy-0.28.0.dist-info/RECORD
