Metadata-Version: 2.3
Name: finsy
Version: 0.28.0
Summary: P4Runtime Client Library
License: Apache-2.0
Author: Bill Fisher
Author-email: william.w.fisher@gmail.com
Requires-Python: >=3.10,<4.0
Classifier: Development Status :: 4 - Beta
Classifier: Framework :: AsyncIO
Classifier: License :: OSI Approved :: Apache Software License
Classifier: Programming Language :: Python :: 3
Classifier: Programming Language :: Python :: 3.10
Classifier: Programming Language :: Python :: 3.11
Classifier: Programming Language :: Python :: 3.12
Classifier: Programming Language :: Python :: 3.13
Classifier: Typing :: Typed
Provides-Extra: demonet
Requires-Dist: grpcio (>=1.73.1,<2.0.0)
Requires-Dist: parsy (>=2.1.0,<3.0.0)
Requires-Dist: protobuf (>=6.31.1,<7.0.0)
Requires-Dist: pyee (>=13.0.0,<14.0.0)
Requires-Dist: shellous (>=0.38.0,<0.39.0) ; extra == "demonet"
Project-URL: Homepage, https://github.com/byllyfish/finsy
Project-URL: Issue Tracker, https://github.com/byllyfish/finsy/issues
Project-URL: Release Notes, https://github.com/byllyfish/finsy/blob/main/CHANGELOG.md
